README.md
am/__init__.py
am/manage.py
am/data/__init__.py
am/data/segmenter/part/overhang.STL
am/data/segmenter/part/overhang.gcode
am/data/solver/material/SS316L.ini
am/data/solver/material/__init__.py
am/data/solver/mesh/__init__.py
am/data/solver/mesh/scale_millimeter.ini
am/data/solver/model/ss316.pkl
am/data/workspace/manage.py
am/portfolio/__init__.py
am/portfolio/base.py
am/portfolio/workspace.py
am/segmenter/__init__.py
am/segmenter/base.py
am/segmenter/gcode.py
am/simulation/__init__.py
am/simulation/base.py
am/simulation/visualize.py
am/solver/__init__.py
am/solver/base.py
am/solver/heat_diffusion.py
am/solver/models.py
am/solver/types.py
am/solver/utils.py
am/workspace/__init__.py
am/workspace/base.py
am/workspace/utils.py
am/workspace/segmenter/gcode.py
am/workspace/segmenter/utils.py
am/workspace/simulation/base.py
am/workspace/simulation/utils.py
am/workspace/solver/base.py
am/workspace/solver/utils.py
finetune_am-0.0.1.dist-info/METADATA
finetune_am-0.0.1.dist-info/WHEEL
finetune_am-0.0.1.dist-info/entry_points.txt
finetune_am-0.0.1.dist-info/RECORD
