Metadata-Version: 2.4
Name: finetune-am
Version: 0.0.1
Summary: Additive Manufacturing related tools
Project-URL: Homepage, https://github.com/ppak10/finetune-am
Project-URL: Issues, https://github.com/ppak10/finetune-am/issues
Author-email: Peter Pak <ppak10@gmail.com>, Francis Ogoke <oogoke@andrew.cmu.edu>
Classifier: Operating System :: OS Independent
Classifier: Programming Language :: Python :: 3
Requires-Python: >=3.10
